{"name":"Fiorovizk","skills":[{"id":0,"name":"Overall","rank":563720,"level":1415,"xp":13541552},{"id":1,"name":"Attack","rank":918921,"level":45,"xp":66010},{"id":2,"name":"Defence","rank":616507,"level":68,"xp":651367},{"id":3,"name":"Strength","rank":679497,"level":64,"xp":422799},{"id":4,"name":"Hitpoints","rank":651949,"level":68,"xp":652177},{"id":5,"name":"Ranged","rank":573813,"level":64,"xp":429112},{"id":6,"name":"Prayer","rank":307065,"level":93,"xp":7332586},{"id":7,"name":"Magic","rank":671576,"level":60,"xp":284798},{"id":8,"name":"Cooking","rank":946963,"level":38,"xp":33054},{"id":9,"name":"Woodcutting","rank":1165485,"level":28,"xp":11424},{"id":10,"name":"Fletching","rank":661331,"level":50,"xp":109753},{"id":11,"name":"Fishing","rank":-1,"level":7,"xp":715},{"id":12,"name":"Firemaking","rank":769579,"level":50,"xp":102928},{"id":13,"name":"Crafting","rank":535474,"level":63,"xp":396360},{"id":14,"name":"Smithing","rank":550279,"level":65,"xp":463703},{"id":15,"name":"Mining","rank":549964,"level":67,"xp":571284},{"id":16,"name":"Herblore","rank":683909,"level":28,"xp":11023},{"id":17,"name":"Agility","rank":474785,"level":61,"xp":314311},{"id":18,"name":"Thieving","rank":398943,"level":66,"xp":520382},{"id":19,"name":"Slayer","rank":605171,"level":44,"xp":57521},{"id":20,"name":"Farming","rank":578916,"level":30,"xp":14623},{"id":21,"name":"Runecraft","rank":555802,"level":50,"xp":111339},{"id":22,"name":"Hunter","rank":499585,"level":52,"xp":127113},{"id":23,"name":"Construction","rank":608120,"level":38,"xp":32918},{"id":24,"name":"Summoning","rank":510631,"level":42,"xp":48664},{"id":25,"name":"Dungeoneering","rank":586058,"level":42,"xp":49231},{"id":26,"name":"Divination","rank":527657,"level":31,"xp":15990},{"id":27,"name":"Invention","rank":-1,"level":1,"xp":0},{"id":28,"name":"Archaeology","rank":393125,"level":31,"xp":16131},{"id":29,"name":"Necromancy","rank":229694,"level":69,"xp":694236}],"activities":[{"id":0,"name":"Bounty Hunters","rank":-1,"score":0},{"id":1,"name":"Bounty Hunter Rogues","rank":-1,"score":0},{"id":2,"name":"Dominion Tower","rank":-1,"score":0},{"id":3,"name":"The Crucible","rank":-1,"score":0},{"id":4,"name":"Castle Wars Games","rank":-1,"score":0},{"id":5,"name":"B.A Attackers","rank":-1,"score":0},{"id":6,"name":"B.A Defenders","rank":-1,"score":0},{"id":7,"name":"B.A Collectors","rank":-1,"score":0},{"id":8,"name":"B.A Healers","rank":-1,"score":0},{"id":9,"name":"Duel Tournament","rank":-1,"score":0},{"id":10,"name":"Mobilising Armies","rank":-1,"score":0},{"id":11,"name":"Conquest","rank":-1,"score":0},{"id":12,"name":"Fist of Guthix","rank":-1,"score":0},{"id":13,"name":"GG: Resource Race","rank":-1,"score":0},{"id":14,"name":"GG: Athletics","rank":-1,"score":0},{"id":17,"name":"WE2 Armadyl lifetime contribution","rank":-1,"score":0},{"id":18,"name":"WE2 Bandos lifetime contribution","rank":-1,"score":0},{"id":19,"name":"WE2 Armadyl PvP kills","rank":-1,"score":0},{"id":20,"name":"WE2 Bandos PvP kills","rank":-1,"score":0},{"id":21,"name":"Heist: Guard Prestige","rank":-1,"score":0},{"id":22,"name":"Heist: Robber Prestige","rank":-1,"score":0},{"id":23,"name":"CFP: 5 game average","rank":-1,"score":0},{"id":24,"name":"Cow tips","rank":-1,"score":0},{"id":25,"name":"Rats Slaughtered","rank":-1,"score":0},{"id":26,"name":"RuneScore","rank":506429,"score":1680},{"id":27,"name":"Clue Scrolls (easy)","rank":275126,"score":1},{"id":28,"name":"Clue Scrolls (medium)","rank":-1,"score":0},{"id":29,"name":"Clue Scrolls (hard)","rank":-1,"score":0},{"id":30,"name":"Clue Scrolls (elite)","rank":-1,"score":0},{"id":31,"name":"Clue Scrolls (master)","rank":-1,"score":0},{"id":32,"name":"Leagues: CATALYST","rank":-1,"score":0}]}